AUTHORS
LICENSE
MANIFEST.in
README.md
ez_setup.py
setup.py
mongokit/__init__.py
mongokit/auth.py
mongokit/collection.py
mongokit/connection.py
mongokit/cursor.py
mongokit/database.py
mongokit/document.py
mongokit/grid.py
mongokit/helpers.py
mongokit/master_slave_connection.py
mongokit/migration.py
mongokit/mongo_exceptions.py
mongokit/operators.py
mongokit/paginator.py
mongokit/schema_document.py
mongokit/versioned_document.py
mongokit_py3.egg-info/PKG-INFO
mongokit_py3.egg-info/SOURCES.txt
mongokit_py3.egg-info/dependency_links.txt
mongokit_py3.egg-info/not-zip-safe
mongokit_py3.egg-info/requires.txt
mongokit_py3.egg-info/top_level.txt
tests/test_api.py
tests/test_auth.py
tests/test_autoref.py
tests/test_custom_types.py
tests/test_descriptors.py
tests/test_ext_mongodb_auth.py
tests/test_gridfs.py
tests/test_helpers.py
tests/test_i18n.py
tests/test_index.py
tests/test_inheritance.py
tests/test_inherited_queries.py
tests/test_json.py
tests/test_mapreduce.py
tests/test_migration.py
tests/test_schemaless.py
tests/test_structure.py
tests/test_types.py
tests/test_versioned.py